FortiCareCli/customLogging.py
FortiCareCli/fccli.py
FortiCareCli-1.0.2.data/scripts/fccli
FortiCareCli-1.0.2.data/scripts/fccli.py
FortiCareCli-1.0.2.dist-info/LICENSE
FortiCareCli-1.0.2.dist-info/METADATA
FortiCareCli-1.0.2.dist-info/WHEEL
FortiCareCli-1.0.2.dist-info/top_level.txt
FortiCareCli-1.0.2.dist-info/RECORD
