Metadata-Version: 2.1
Name: FortiCareCli
Version: 1.0.2
Summary: Example application to interact with FortiCare library
Home-page: https://pypi.org/project/FortiCareCli/
Author: See "Authors" section
Author-email: 
License: MIT
Platform: UNKNOWN
Classifier: Programming Language :: Python :: 3
Classifier: License :: OSI Approved :: MIT License
Classifier: Operating System :: OS Independent
Requires-Python: >=3.6
Requires-Dist: FortiCare (==1.0.2)
